litrwkv/__init__.py
litrwkv/model/__init__.py
litrwkv/model/v7.py
litrwkv-0.0.1a0.dist-info/licenses/LICENSE
litrwkv-0.0.1a0.dist-info/METADATA
litrwkv-0.0.1a0.dist-info/WHEEL
litrwkv-0.0.1a0.dist-info/top_level.txt
litrwkv-0.0.1a0.dist-info/RECORD
