Metadata-Version: 2.4
Name: litrwkv
Version: 0.0.1a0
Summary: A clean RWKV language model implementation(Alpha Version - Under Development)
Author: Ding Wang
License-Expression: Apache-2.0
Project-URL: Homepage, https://github.com/playaswd/litrwkv
Keywords: pytorch,lightning,rwkv,transformer,deep-learning
Classifier: Operating System :: OS Independent
Classifier: Programming Language :: Python :: 3
Requires-Python: >=3.7
License-File: LICENSE
Dynamic: license-file
